qplex/__init__.py
uvic_qplex-0.1.2.dist-info/licenses/LICENSE
uvic_qplex-0.1.2.dist-info/METADATA
uvic_qplex-0.1.2.dist-info/WHEEL
uvic_qplex-0.1.2.dist-info/top_level.txt
uvic_qplex-0.1.2.dist-info/RECORD
