Metadata-Version: 2.4
Name: uvic-qplex
Version: 0.1.2
Summary: an open-source Python library that enables developers to implement combinatorial optimization models and execute them seamlessly on multiple classical and quantum devices using different quantum algorithms.
Author-email: Juan Giraldo <juanfer021299@gmail.com>, Jose Ossorio <joseossorio99@hotmail.com>
License: GPL-3.0
Project-URL: Homepage, https://github.com/JuanGiraldo0212/QPLEX
Project-URL: Documentation, https://juangiraldo0212.github.io/QPLEX/
Project-URL: Repository, https://github.com/JuanGiraldo0212/QPLEX
Project-URL: Issues, https://github.com/JuanGiraldo0212/QPLEX/issues
Classifier: Programming Language :: Python :: 3
Classifier: License :: OSI Approved :: GNU General Public License v3 (GPLv3)
Classifier: Operating System :: OS Independent
Requires-Python: >=3.10.0
License-File: LICENSE
Requires-Dist: docplex~=2.25
Requires-Dist: qiskit~=1.0
Requires-Dist: qiskit_aer
Requires-Dist: qiskit_ibm_runtime
Requires-Dist: qiskit_optimization
Requires-Dist: qiskit_qasm3_import
Requires-Dist: dwave-system~=1.18
Requires-Dist: amazon-braket-sdk~=1.80
Requires-Dist: scipy~=1.10.1
Requires-Dist: dimod~=0.12.4
Requires-Dist: numpy~=1.23.5
Requires-Dist: networkx
Dynamic: license-file
